autonomous_vehicle_simulator-1.0.1.dist-info/licenses/LICENSE
src/__init__.py
src/main.py
src/algorithms/__init__.py
src/algorithms/obstacle_avoidance.py
src/algorithms/path_planning.py
src/core/__init__.py
src/core/config_manager.py
src/core/data_manager.py
src/core/simulation_manager.py
src/gui/__init__.py
src/gui/main_window.py
src/gui/panels/__init__.py
src/gui/panels/ai_navigation_panel.py
src/gui/panels/control_panel.py
src/gui/panels/property_inspector.py
src/gui/panels/scene_tree.py
src/gui/panels/sensor_panel.py
src/gui/panels/timeline.py
src/gui/visualization/__init__.py
src/gui/visualization/viewport_3d.py
src/gui/widgets/__init__.py
src/gui/widgets/toolbar.py
src/simulation/physics_engine.py
autonomous_vehicle_simulator-1.0.1.dist-info/METADATA
autonomous_vehicle_simulator-1.0.1.dist-info/WHEEL
autonomous_vehicle_simulator-1.0.1.dist-info/entry_points.txt
autonomous_vehicle_simulator-1.0.1.dist-info/top_level.txt
autonomous_vehicle_simulator-1.0.1.dist-info/RECORD
