Metadata-Version: 2.4
Name: autonomous-vehicle-simulator
Version: 1.0.1
Summary: Advanced autonomous vehicle simulation with PyQt5 GUI, AI path planning, and real-time physics
Home-page: https://github.com/vision2030/autonomous-vehicle-simulator
Author: Sherin Joseph Roy
Author-email: sherin joseph roy <sherin.joseph2217@gmail.com>
Maintainer-email: sherin joseph roy <sherin.joseph2217@gmail.com>
License: MIT
Project-URL: Homepage, https://github.com/vision2030/autonomous-vehicle-simulator
Project-URL: Documentation, https://github.com/vision2030/autonomous-vehicle-simulator/blob/main/README.md
Project-URL: Repository, https://github.com/vision2030/autonomous-vehicle-simulator
Project-URL: Bug Tracker, https://github.com/vision2030/autonomous-vehicle-simulator/issues
Keywords: autonomous,vehicle,simulation,robotics,ai,path-planning,physics,pyqt5,3d-visualization,machine-learning,reinforcement-learning
Platform: Linux
Platform: Windows
Platform: macOS
Classifier: Development Status :: 4 - Beta
Classifier: Intended Audience :: Developers
Classifier: Intended Audience :: Science/Research
Classifier: License :: OSI Approved :: MIT License
Classifier: Operating System :: OS Independent
Classifier: Programming Language :: Python :: 3
Classifier: Programming Language :: Python :: 3.8
Classifier: Programming Language :: Python :: 3.9
Classifier: Programming Language :: Python :: 3.10
Classifier: Programming Language :: Python :: 3.11
Classifier: Programming Language :: Python :: 3.12
Classifier: Topic :: Scientific/Engineering :: Artificial Intelligence
Classifier: Topic :: Scientific/Engineering :: Physics
Classifier: Topic :: Software Development :: Libraries :: Python Modules
Classifier: Topic :: Multimedia :: Graphics :: 3D Rendering
Classifier: Topic :: Scientific/Engineering :: Visualization
Requires-Python: >=3.8
License-File: LICENSE
Requires-Dist: PyQt5>=5.15.0
Requires-Dist: numpy>=1.21.0
Requires-Dist: pybullet>=3.2.0
Requires-Dist: PyYAML>=6.0
Requires-Dist: PyOpenGL>=3.1.0
Provides-Extra: dev
Requires-Dist: pytest>=6.0; extra == "dev"
Requires-Dist: pytest-cov>=2.0; extra == "dev"
Requires-Dist: black>=21.0; extra == "dev"
Requires-Dist: flake8>=3.8; extra == "dev"
Requires-Dist: mypy>=0.800; extra == "dev"
Requires-Dist: pre-commit>=2.0; extra == "dev"
Provides-Extra: docs
Requires-Dist: sphinx>=4.0; extra == "docs"
Requires-Dist: sphinx-rtd-theme>=1.0; extra == "docs"
Requires-Dist: myst-parser>=0.15; extra == "docs"
Dynamic: author
Dynamic: home-page
Dynamic: license-file
Dynamic: platform
Dynamic: requires-python
